heparchy/__init__.py
heparchy/_version.py
heparchy/data.py
heparchy/hepmc.py
heparchy/read.py
heparchy/utils.py
heparchy/write.py
heparchy-0.1.2.dist-info/LICENSE.txt
heparchy-0.1.2.dist-info/METADATA
heparchy-0.1.2.dist-info/WHEEL
heparchy-0.1.2.dist-info/top_level.txt
heparchy-0.1.2.dist-info/RECORD
