Metadata-Version: 2.1
Name: heparchy
Version: 0.1.2
Summary: Hierarchical particle physics data I/O.
Home-page: https://github.com/jacanchaplais/heparchy
Author: Jacan Chaplais
Author-email: jacanchaplais@gmail.com
License: BSD 3-Clause License
Platform: UNKNOWN
Classifier: Programming Language :: Python :: 3
Classifier: License :: OSI Approved :: BSD License
Classifier: Operating System :: OS Independent
License-File: LICENSE.txt
Requires-Dist: attrs
Requires-Dist: numpy
Requires-Dist: vector
Requires-Dist: networkx
Requires-Dist: pyhepmc-ng
Requires-Dist: h5py
Requires-Dist: typicle
